MyDiPy-0.0.1.dist-info/DESCRIPTION.rst
MyDiPy-0.0.1.dist-info/METADATA
MyDiPy-0.0.1.dist-info/RECORD
MyDiPy-0.0.1.dist-info/WHEEL
MyDiPy-0.0.1.dist-info/metadata.json
MyDiPy-0.0.1.dist-info/top_level.txt
mydipy/__init__.py
mydipy/cast.py
mydipy/inherit.py
mydipy/type_check.py
mydipy/typed.py
mydipy/types.py
